uplid/__init__.py
uplid/py.typed
uplid/uplid.py
uplid-1.0.1.dist-info/WHEEL
uplid-1.0.1.dist-info/METADATA
uplid-1.0.1.dist-info/RECORD
