Metadata-Version: 2.4
Name: uplid
Version: 1.0.1
Summary: Universal Prefixed Literal IDs - type-safe, human-readable identifiers
Keywords: uuid,id,identifier,pydantic,type-safe,uuid7
Author: ZVS
Author-email: ZVS <zvs@daswolf.dev>
License-Expression: MIT
Classifier: Development Status :: 5 - Production/Stable
Classifier: Framework :: Pydantic :: 2
Classifier: Intended Audience :: Developers
Classifier: License :: OSI Approved :: MIT License
Classifier: Operating System :: OS Independent
Classifier: Programming Language :: Python :: 3.14
Classifier: Typing :: Typed
Requires-Dist: pydantic>=2.10
Requires-Python: >=3.14
Project-URL: Homepage, https://github.com/zvsdev/uplid
Project-URL: Repository, https://github.com/zvsdev/uplid
